ecasbot/__init__.py
ecasbot/chkmsg.py
ecasbot/chkusr.py
ecasbot/exceptions.py
ecasbot/extractor.py
ecasbot/permissions.py
ecasbot/ranges.py
ecasbot/settings.py
ecasbot/messages/__init__.py
ecasbot/messages/factory.py
ecasbot/messages/locales/__init__.py
ecasbot/messages/locales/en.py
ecasbot/messages/locales/ru.py
ecasbot/scripts/__init__.py
ecasbot/scripts/runbot.py
ecasbot-1.8.3.dist-info/LICENSE
ecasbot-1.8.3.dist-info/METADATA
ecasbot-1.8.3.dist-info/WHEEL
ecasbot-1.8.3.dist-info/entry_points.txt
ecasbot-1.8.3.dist-info/top_level.txt
ecasbot-1.8.3.dist-info/RECORD
