Metadata-Version: 2.1
Name: ecasbot
Version: 1.8.3
Summary: EC AntiSpam bot for the Telegram messenger
Author-email: Vitaly Zaitsev <vitaly@easycoding.org>
License: GPL-3.0-or-later
Project-URL: homepage, https://github.com/xvitaly/ecasbot
Project-URL: documentation, https://github.com/xvitaly/ecasbot/blob/master/docs/README.md
Project-URL: repository, https://github.com/xvitaly/ecasbot
Keywords: anti-spam,bot,database-less,protection,telegram,telegram-api,telegram-bot
Classifier: Programming Language :: Python :: 3
Classifier: License :: OSI Approved :: GNU General Public License v3 (GPLv3)
Classifier: Operating System :: OS Independent
Requires-Python: >=3.6
License-File: LICENSE
Requires-Dist: requests (>=2.28.0)
Requires-Dist: pytelegrambotapi (>=4.12.0)
Requires-Dist: emoji (>=2.5.1)
Provides-Extra: deploy
Requires-Dist: pyinstaller (>=5.7.0) ; extra == 'deploy'
Provides-Extra: test
Requires-Dist: tox (>=3.27.0) ; extra == 'test'
